sepi_point/test/ERR1191752.results.tsv
sepi_point/test/ERR1191752.vcf
sepi_point/test/ERR1191752.log
sepi_point/sepi_point_batch.py
sepi_point/example_data/SRR7141667.vcf
sepi_point/example_data/SRR7141667.fasta
sepi_point/example_data/ERR1191752.vcf
sepi_point/sepi_point_summary.py
sepi_point/__init__.py
sepi_point/mutation_finder.py
sepi_point/seqtools.py
sepi_point/db/sequences.fasta.amb
sepi_point/db/sequences.fasta.bwt
sepi_point/db/sequences.fasta.fai
sepi_point/db/sequences.fasta.sa
sepi_point/db/sequences.fasta.ann
sepi_point/db/sequences.fasta
sepi_point/db/sequences.fasta.pac
sepi_point/db/mutations.tsv
sepi_point/sepi_point.py
sepi_point-1.0.0.dist-info/WHEEL
sepi_point-1.0.0.dist-info/entry_points.txt
sepi_point-1.0.0.dist-info/METADATA
sepi_point-1.0.0.dist-info/RECORD
