Metadata-Version: 2.3
Name: sepi-point
Version: 1.0.0
Summary: Detection of point mutation-mediated antimicrobial resistance in Staphylococcus epidermidis 
Requires-Dist: pandas
Requires-Dist: numpy
Requires-Python: >=3.9
